{"version":1,"resource":"file:///home/abeer/Code/Python_learning/clean.ipynb","entries":[{"id":"h7jb.ipynb","timestamp":1735845278779},{"id":"rfEk.ipynb","timestamp":1735845289259},{"id":"8WX9.ipynb","timestamp":1735845299282},{"id":"iiko.ipynb","timestamp":1735845386474},{"id":"M8jI.ipynb","timestamp":1735845512673},{"id":"81pS.ipynb","timestamp":1735845567960},{"id":"hN3A.ipynb","timestamp":1735845960910},{"id":"iAk1.ipynb","timestamp":1735846005565},{"id":"1Qkc.ipynb","timestamp":1735846148263},{"id":"N6uE.ipynb","timestamp":1735846221942},{"id":"IK7d.ipynb","timestamp":1735846254600},{"id":"WSsN.ipynb","timestamp":1735846363116},{"id":"KLlG.ipynb","timestamp":1735846402024},{"id":"qX40.ipynb","timestamp":1735847631516},{"id":"k9Tc.ipynb","timestamp":1735847679963},{"id":"yukr.ipynb","timestamp":1735847949712},{"id":"qbAA.ipynb","timestamp":1735848126231},{"id":"5Oqe.ipynb","timestamp":1735848193732},{"id":"aAmJ.ipynb","timestamp":1735848278993},{"id":"W8uI.ipynb","timestamp":1735848709265},{"id":"XoM0.ipynb","timestamp":1735848805042},{"id":"q7tx.ipynb","timestamp":1735848896198},{"id":"Xyx8.ipynb","timestamp":1735851473439},{"id":"Y4ef.ipynb","timestamp":1735858784804},{"id":"Y9YH.ipynb","timestamp":1735858816768},{"id":"KEWz.ipynb","timestamp":1735858843758},{"id":"pPIK.ipynb","timestamp":1735858892819},{"id":"vwYe.ipynb","timestamp":1735859038418},{"id":"qR6E.ipynb","timestamp":1735859054871},{"id":"Ed9o.ipynb","timestamp":1735872059829},{"id":"UXoh.ipynb","timestamp":1735877938666}]}