{"version":1,"resource":"file:///home/abeer/Code/Python_learning/Data_cleaning.ipynb","entries":[{"id":"P9Ln.ipynb","timestamp":1736053128461},{"id":"6cJZ.ipynb","timestamp":1736053147798},{"id":"G6oP.ipynb","timestamp":1736053175735},{"id":"rQcv.ipynb","timestamp":1736053196361},{"id":"9I5h.ipynb","timestamp":1736053214205},{"id":"unhM.ipynb","timestamp":1736053240988},{"id":"0iWO.ipynb","timestamp":1736053266165},{"id":"XzPX.ipynb","timestamp":1736053301076},{"id":"O2qp.ipynb","timestamp":1736053442893},{"id":"7yOB.ipynb","timestamp":1736053471777},{"id":"0ZnK.ipynb","timestamp":1736053568361},{"id":"iFtr.ipynb","timestamp":1736053585761},{"id":"mg09.ipynb","timestamp":1736053600281},{"id":"ODnA.ipynb","timestamp":1736053655849},{"id":"9JAX.ipynb","timestamp":1736053684155},{"id":"vWDp.ipynb","timestamp":1736053741699},{"id":"LprG.ipynb","timestamp":1736053781666},{"id":"Mm4K.ipynb","timestamp":1736053802946},{"id":"N4FE.ipynb","source":"edit","timestamp":1736053815117},{"id":"Et74.ipynb","timestamp":1736053818213},{"id":"GCfu.ipynb","timestamp":1736054190436},{"id":"rOeC.ipynb","timestamp":1736054217450},{"id":"RhZC.ipynb","timestamp":1736054267537},{"id":"HFH0.ipynb","timestamp":1736054322218},{"id":"UN9w.ipynb","timestamp":1736054366775},{"id":"tB9Z.ipynb","timestamp":1736054428029},{"id":"P3DS.ipynb","timestamp":1736054546496},{"id":"AGJD.ipynb","timestamp":1736054575580},{"id":"UStV.ipynb","timestamp":1736054587890},{"id":"Nqja.ipynb","timestamp":1736054600350},{"id":"87Y0.ipynb","timestamp":1736054649204},{"id":"qAYj.ipynb","timestamp":1736054680887},{"id":"cdGi.ipynb","timestamp":1736054735854},{"id":"3QkU.ipynb","timestamp":1736054779341},{"id":"Rgp5.ipynb","timestamp":1736054836098},{"id":"bk33.ipynb","timestamp":1736054899569},{"id":"YoxZ.ipynb","timestamp":1736054930179},{"id":"H5zn.ipynb","timestamp":1736054969636},{"id":"cafw.ipynb","timestamp":1736055000690},{"id":"F1Dn.ipynb","timestamp":1736055100651},{"id":"2y35.ipynb","timestamp":1736055114041},{"id":"9Ulr.ipynb","timestamp":1736055151544},{"id":"4NXJ.ipynb","timestamp":1736055205198},{"id":"qmrT.ipynb","timestamp":1736055342539},{"id":"0jKt.ipynb","timestamp":1736055442930},{"id":"ReLW.ipynb","timestamp":1736055502434},{"id":"B5Pk.ipynb","timestamp":1736055577125},{"id":"m4wc.ipynb","timestamp":1736055598885},{"id":"sXkv.ipynb","timestamp":1736055629572},{"id":"sUmD.ipynb","timestamp":1736055662129}]}